Workbook

Sheet Inputs
A1: AGORA JOBS — CREDIT PRICING CALCULATOR (edit the gold cells) — ILLUSTRATIVE • PRICES NOT FINAL
A3: 1) Model pricing (USD per 1,000,000 tokens)
A4: Model | B4: Input $/1M | C4: Output $/1M
A5: Opus 4.8 (CV + cover letter) | B5: 5 | C5: 25
A6: Sonnet 4.6 (Ari advanced tasks) | B6: 3 | C6: 15
A7: Haiku 4.5 (Ari normal chat) | B7: 1 | C7: 5
A9: 2) Currency
A10: USD → EUR rate | B10: 0.92
A12: 3) Token usage per action (per generation / per message)
A13: Action | B13: Model | C13: Input tokens | D13: Output tokens | E13: Input $/1M | F13: Output $/1M
A14: CV generation | B14: Opus 4.8 | C14: 3500 | D14: 1500 | E14: =$B$5 | F14: =$C$5
A15: Cover letter | B15: Opus 4.8 | C15: 4000 | D15: 1000 | E15: =$B$5 | F15: =$C$5
A16: Ari chat message | B16: Haiku 4.5 | C16: 1500 | D16: 400 | E16: =$B$7 | F16: =$C$7
A17: Ari advanced task | B17: Sonnet 4.6 | C17: 6000 | D17: 1500 | E17: =$B$6 | F17: =$C$6
A19: 4) Ari session shape
A20: Messages per session | B20: 20
A21: Escalation to Sonnet (% of sessions) | B21: 0.3
A22: Sonnet tasks per escalated session | B22: 1
A24: 5) Typical student usage (per month)
A25: CVs generated / month | B25: 4
A26: Cover letters / month | B26: 12
A27: Ari sessions / month | B27: 8
A29: 6) Commercial assumptions
A30: Target gross margin | B30: 0.8
A31: Stripe % fee | B31: 0.029
A32: Stripe fixed fee (€ / transaction) | B32: 0.25
A33: Credit purchases / month (transactions) | B33: 1
A35: Gold cells are inputs — change any of them and every sheet recalculates.
A36: Credit price (€/credit), pack sizes and the Free allowance are NOT decided yet. All euro figures below are illustrative cost-ratio anchors for modelling only.

Sheet Credit Pricing
A1: PER-ACTION CREDIT PRICING — ILLUSTRATIVE • PRICES NOT FINAL
A3: Action | B3: Input tok | C3: Output tok | D3: COGS $/action | E3: COGS €/action | F3: Credits / action | G3: COGS €/credit | H3: Retail €/credit | I3: Price €/action | J3: Gross margin
A4: CV generation | B4: =Inputs!C14 | C4: =Inputs!D14 | D4: =B4*Inputs!E14/1000000+C4*Inputs!F14/1000000 | E4: =D4*Inputs!$B$10 | F4: 16 | G4: =E4/F4 | H4: =$B$13 | I4: =F4*H4 | J4: =(I4-E4)/I4
A5: Cover letter | B5: =Inputs!C15 | C5: =Inputs!D15 | D5: =B5*Inputs!E15/1000000+C5*Inputs!F15/1000000 | E5: =D5*Inputs!$B$10 | F5: 13 | G5: =E5/F5 | H5: =$B$13 | I5: =F5*H5 | J5: =(I5-E5)/I5
A6: Ari chat message | B6: =Inputs!C16 | C6: =Inputs!D16 | D6: =B6*Inputs!E16/1000000+C6*Inputs!F16/1000000 | E6: =D6*Inputs!$B$10 | F6: 1 | G6: =E6/F6 | H6: =$B$13 | I6: =F6*H6 | J6: =(I6-E6)/I6
A7: Ari advanced task | B7: =Inputs!C17 | C7: =Inputs!D17 | D7: =B7*Inputs!E17/1000000+C7*Inputs!F17/1000000 | E7: =D7*Inputs!$B$10 | F7: 12 | G7: =E7/F7 | H7: =$B$13 | I7: =F7*H7 | J7: =(I7-E7)/I7
A9: Global credit price
A10: Blended COGS €/credit | B10: ='Student Usage'!B10
A11: Target gross margin | B11: =Inputs!B30
A12: Retail €/credit (solved from margin) | B12: =B10/(1-B11)
A13: Retail €/credit USED (override here) | B13: =B12
A15: Credits per action default to the cost ratio vs one Ari chat message
A16: (1 message = 1 credit). Override the 'Credits / action' column to set round prices.
A17: B13 is a formula by default — type a number there to fix your own credit price.
A18: ⚠ Retail €/credit is illustrative (solved from the target margin). No price is finalised — type your own value in B13 to test scenarios.

Sheet Student Usage
A1: TYPICAL STUDENT — MONTHLY ECONOMICS — ILLUSTRATIVE • PRICES NOT FINAL
A3: Action | B3: Qty / month | C3: Credits each | D3: Total credits | E3: COGS € each | F3: Total COGS €
A4: CV generation | B4: =Inputs!B25 | C4: ='Credit Pricing'!F4 | D4: =B4*C4 | E4: ='Credit Pricing'!E4 | F4: =B4*E4
A5: Cover letter | B5: =Inputs!B26 | C5: ='Credit Pricing'!F5 | D5: =B5*C5 | E5: ='Credit Pricing'!E5 | F5: =B5*E5
A6: Ari chat message | B6: =Inputs!B27*Inputs!B20 | C6: ='Credit Pricing'!F6 | D6: =B6*C6 | E6: ='Credit Pricing'!E6 | F6: =B6*E6
A7: Ari advanced task | B7: =Inputs!B27*Inputs!B21*Inputs!B22 | C7: ='Credit Pricing'!F7 | D7: =B7*C7 | E7: ='Credit Pricing'!E7 | F7: =B7*E7
A8: TOTAL / month | D8: =SUM(D4:D7) | F8: =SUM(F4:F7)
A10: Blended COGS €/credit | B10: =F8/D8
A12: Monthly economics at the chosen credit price
A13: Credits used / month | B13: =D8
A14: Retail €/credit | B14: ='Credit Pricing'!B13
A15: Gross revenue €/month | B15: =B13*B14
A16: Stripe fees €/month | B16: =B15*Inputs!B31+Inputs!B33*Inputs!B32
A17: Net revenue €/month | B17: =B15-B16
A18: AI cost (COGS) €/month | B18: =F8
A19: Gross profit €/month | B19: =B17-B18
A20: Gross margin % | B20: =B19/B15
A22: Versus the old subscription pricing
A23: Effective price student pays / month | B23: =B15
A24: Old weekly band | B24: €4.99 – €6.99 /wk
A25: Old monthly band | B25: €5.99 – €9.99 /mo
A27: Credits scale revenue with real usage; light users pay less, heavy users pay more — margin holds either way.

Sheet Credit Packs
A1: CREDIT PACK PRICING — ILLUSTRATIVE • PRICES NOT FINAL
A3: Pack (credits) | B3: Price € | C3: AI cost € | D3: Net after Stripe € | E3: Margin | F3: Lasts a typical student
A4: 100 | B4: =A4*'Credit Pricing'!B13 | C4: =A4*'Student Usage'!B10 | D4: =B4-(B4*Inputs!B31+Inputs!B32) | E4: =(D4-C4)/B4 | F4: =A4/'Student Usage'!D8
A5: 250 | B5: =A5*'Credit Pricing'!B13 | C5: =A5*'Student Usage'!B10 | D5: =B5-(B5*Inputs!B31+Inputs!B32) | E5: =(D5-C5)/B5 | F5: =A5/'Student Usage'!D8
A6: 500 | B6: =A6*'Credit Pricing'!B13 | C6: =A6*'Student Usage'!B10 | D6: =B6-(B6*Inputs!B31+Inputs!B32) | E6: =(D6-C6)/B6 | F6: =A6/'Student Usage'!D8
A7: 1000 | B7: =A7*'Credit Pricing'!B13 | C7: =A7*'Student Usage'!B10 | D7: =B7-(B7*Inputs!B31+Inputs!B32) | E7: =(D7-C7)/B7 | F7: =A7/'Student Usage'!D8
A9: Margin per pack is slightly below target because each pack is a single Stripe transaction (fixed € fee). Bigger packs = better margin.

Sheet Sensitivity
A1: SENSITIVITY — CREDIT PRICE vs MARGIN & PROFIT — ILLUSTRATIVE • PRICES NOT FINAL
A3: Per typical student (uses ='Student Usage'!D8 credits/month). Sweep the retail price per credit:
A5: Retail €/credit | B5: Revenue €/mo | C5: Gross margin | D5: Net profit /100 users €/mo
A6: 0.01 | B6: =A6*'Student Usage'!D8 | C6: =((B6-(B6*Inputs!B31+Inputs!B33*Inputs!B32))-'Student Usage'!F8)/B6 | D6: =((B6-(B6*Inputs!B31+Inputs!B33*Inputs!B32))-'Student Usage'!F8)*100
A7: 0.012 | B7: =A7*'Student Usage'!D8 | C7: =((B7-(B7*Inputs!B31+Inputs!B33*Inputs!B32))-'Student Usage'!F8)/B7 | D7: =((B7-(B7*Inputs!B31+Inputs!B33*Inputs!B32))-'Student Usage'!F8)*100
A8: 0.014 | B8: =A8*'Student Usage'!D8 | C8: =((B8-(B8*Inputs!B31+Inputs!B33*Inputs!B32))-'Student Usage'!F8)/B8 | D8: =((B8-(B8*Inputs!B31+Inputs!B33*Inputs!B32))-'Student Usage'!F8)*100
A9: 0.016 | B9: =A9*'Student Usage'!D8 | C9: =((B9-(B9*Inputs!B31+Inputs!B33*Inputs!B32))-'Student Usage'!F8)/B9 | D9: =((B9-(B9*Inputs!B31+Inputs!B33*Inputs!B32))-'Student Usage'!F8)*100
A10: 0.018 | B10: =A10*'Student Usage'!D8 | C10: =((B10-(B10*Inputs!B31+Inputs!B33*Inputs!B32))-'Student Usage'!F8)/B10 | D10: =((B10-(B10*Inputs!B31+Inputs!B33*Inputs!B32))-'Student Usage'!F8)*100
A11: 0.02 | B11: =A11*'Student Usage'!D8 | C11: =((B11-(B11*Inputs!B31+Inputs!B33*Inputs!B32))-'Student Usage'!F8)/B11 | D11: =((B11-(B11*Inputs!B31+Inputs!B33*Inputs!B32))-'Student Usage'!F8)*100
A12: 0.025 | B12: =A12*'Student Usage'!D8 | C12: =((B12-(B12*Inputs!B31+Inputs!B33*Inputs!B32))-'Student Usage'!F8)/B12 | D12: =((B12-(B12*Inputs!B31+Inputs!B33*Inputs!B32))-'Student Usage'!F8)*100
A13: 0.03 | B13: =A13*'Student Usage'!D8 | C13: =((B13-(B13*Inputs!B31+Inputs!B33*Inputs!B32))-'Student Usage'!F8)/B13 | D13: =((B13-(B13*Inputs!B31+Inputs!B33*Inputs!B32))-'Student Usage'!F8)*100
A15: Cost of goods is tiny (cents/month), so margin is driven almost entirely by the price you set per credit.
